paig/README.md
paig/VERSION
paig/__init__.py
paig/__main__.py
paig/launcher.py
paig/routers.py
paig/run_unit_test.sh
paig/server.py
paig/alembic_db/README.md
paig/alembic_db/__init__.py
paig/alembic_db/alembic.ini
paig/alembic_db/env.py
paig/alembic_db/script.py.mako
paig/alembic_db/versions/1900f97ae685_added_config_history_id_colun_in_eval_.py
paig/alembic_db/versions/1b4de1560f7a_added_application_key_to_ai_application_.py
paig/alembic_db/versions/1fced03debf8_access_audits_table_added.py
paig/alembic_db/versions/2d992e5994c8_evaluation_reports_new_columns_added.py
paig/alembic_db/versions/3e84bb67bced_added_tenant_id_for_guardrail_tables_.py
paig/alembic_db/versions/5e805b526efa_add_tenant.py
paig/alembic_db/versions/67a256363095_added_guardrail_service_tables.py
paig/alembic_db/versions/701ddf55a1b4_added_evaluation_tables.py
paig/alembic_db/versions/9249428e19b0_added_encryption_key_table.py
paig/alembic_db/versions/99a43bcdbea1_added_encryption_master_key_table.py
paig/alembic_db/versions/a7d20ed3c5b4_added_governance_service_tables.py
paig/alembic_db/versions/a95b604c47fb_added_guardrail_details_column_to_ai_app.py
paig/alembic_db/versions/a9c87d84b974_added_paig_api_key_and_encryption_level.py
paig/alembic_db/versions/d016d5e1fe5a_initial_migrations.py
paig/alembic_db/versions/db6e7b60cb0a_adding_new_encryption_type_in_enum.py
paig/alembic_db/versions/dd5bdf787fa1_added_admin_audit_tables.py
paig/alembic_db/versions/ea2679878e00_add_tenant_id_support_for_eval.py
paig/alembic_db/versions/f32841395145_add_toxic_tag.py
paig/alembic_db/versions/f36705415cd9_added_predefined_response_templates.py
paig/api/__init__.py
paig/api/apikey/__init__.py
paig/api/apikey/routers.py
paig/api/apikey/utils.py
paig/api/apikey/api_schemas/__init__.py
paig/api/apikey/api_schemas/paig_api_key.py
paig/api/apikey/controllers/__init__.py
paig/api/apikey/controllers/paig_api_key_controller.py
paig/api/apikey/controllers/paig_level1_encryption_key_controller.py
paig_server-0.0.11.dist-info/METADATA
paig_server-0.0.11.dist-info/WHEEL
paig_server-0.0.11.dist-info/entry_points.txt
paig_server-0.0.11.dist-info/RECORD
