Metadata-Version: 2.4
Name: paig-server
Version: 0.0.11
Summary: PAIG Server
Project-URL: Homepage, https://github.com/privacera/paig
Project-URL: Bug Tracker, https://github.com/privacera/paig/issues
Author-email: Privacera  <support@privacera.com>
License:                                  Apache License
Keywords: Chatbot,Governance,PAIG,PAIG-Server,Privacy,Security
Classifier: License :: Other/Proprietary License
Classifier: Operating System :: OS Independent
Classifier: Programming Language :: Python :: 3
Requires-Python: >=3.10
Requires-Dist: aiosqlite
Requires-Dist: alembic
Requires-Dist: alt-profanity-check==1.5.0
Requires-Dist: apscheduler
Requires-Dist: bcrypt
Requires-Dist: boto3==1.34.20
Requires-Dist: cryptography==41.0.4
Requires-Dist: fastapi
Requires-Dist: fasteners
Requires-Dist: greenlet
Requires-Dist: httpx
Requires-Dist: jproperties
Requires-Dist: numpy==1.26.4
Requires-Dist: opentelemetry-distro==0.45b0
Requires-Dist: opentelemetry-exporter-otlp==1.24.0
Requires-Dist: paig-authorizer-core>=0.0.3
Requires-Dist: paig-common
Requires-Dist: paig-evaluation>=0.0.2
Requires-Dist: passlib
Requires-Dist: posthog
Requires-Dist: presidio-analyzer==2.2.353
Requires-Dist: presidio-anonymizer==2.2.353
Requires-Dist: psutil
Requires-Dist: pydantic[email]
Requires-Dist: python-jose
Requires-Dist: pytz
Requires-Dist: scipy==1.14.1
Requires-Dist: sqlalchemy
Requires-Dist: starlette-request-id
Requires-Dist: urllib3
Requires-Dist: uvicorn
Provides-Extra: dev
Requires-Dist: pytest; extra == 'dev'
Requires-Dist: pytest-asyncio; extra == 'dev'
Requires-Dist: pytest-cov; extra == 'dev'
Requires-Dist: pytest-mock; extra == 'dev'
Requires-Dist: uvicorn[standard]; extra == 'dev'
Provides-Extra: opensearch
Requires-Dist: boto3>=1.28.57; extra == 'opensearch'
Requires-Dist: opensearch-py; extra == 'opensearch'
